README.rst
setup.py
outbrain/__init__.py
outbrain.egg-info/PKG-INFO
outbrain.egg-info/SOURCES.txt
outbrain.egg-info/dependency_links.txt
outbrain.egg-info/requires.txt
outbrain.egg-info/top_level.txt
test/test_outbrain.py