Metadata-Version: 1.1
Name: outbrain
Version: 0.0.9
Summary: Wrapper for the Outbrain Amplify API
Home-page: https://github.com/andessen/python-outbrain
Author: Brian Mason
Author-email: bmsaon@simplereach.com
License: LGPL 2.1 or later
Keywords: outbrain,api,amplify
Platform: UNKNOWN
Classifier: Intended Audience :: Developers
